pluca/__init__.py
pluca/benchmark.py
pluca/cache.py
pluca/comp.py
pluca/dbm.py
pluca/file.py
pluca/memory.py
pluca/null.py
pluca/py.typed
pluca/sql.py
pluca/sqlite3.py
pluca/test.py
pluca/utils.py
pluca-0.6.2.dist-info/LICENSE.txt
pluca-0.6.2.dist-info/WHEEL
pluca-0.6.2.dist-info/METADATA
pluca-0.6.2.dist-info/RECORD
